README.txt
setup.cfg
setup.py
docs/HISTORY.txt
docs/INSTALL.txt
docs/LICENSE.GPL
docs/LICENSE.txt
plone/__init__.py
plone.principalsource.egg-info/PKG-INFO
plone.principalsource.egg-info/SOURCES.txt
plone.principalsource.egg-info/dependency_links.txt
plone.principalsource.egg-info/entry_points.txt
plone.principalsource.egg-info/namespace_packages.txt
plone.principalsource.egg-info/not-zip-safe
plone.principalsource.egg-info/requires.txt
plone.principalsource.egg-info/top_level.txt
plone/principalsource/__init__.py
plone/principalsource/configure.zcml
plone/principalsource/interfaces.py
plone/principalsource/source.py
plone/principalsource/term.py
plone/principalsource/tests.py