Metadata-Version: 1.1
Name: plone.principalsource
Version: 1.0
Summary: A queriable source for accessing users and/or groups
Home-page: http://pypi.python.org/pypi/plone.principalsource
Author: Martin Aspeli
Author-email: optilude@gmail.com
License: GPL
Keywords: plone user group principal source
Platform: UNKNOWN
Classifier: Framework :: Plone
Classifier: Programming Language :: Python
Classifier: Topic :: Software Development :: Libraries :: Python Modules
